mtr2mqtt/__init__.py
mtr2mqtt/cli.py
mtr2mqtt/metadata.py
mtr2mqtt/mtr.py
mtr2mqtt/scl.py
mtr2mqtt-0.5.5.dist-info/METADATA
mtr2mqtt-0.5.5.dist-info/WHEEL
mtr2mqtt-0.5.5.dist-info/entry_points.txt
mtr2mqtt-0.5.5.dist-info/top_level.txt
mtr2mqtt-0.5.5.dist-info/RECORD
