Metadata-Version: 2.1
Name: mtr2mqtt
Version: 0.5.5
Summary: MTR receiver readings to MQTT server
Home-page: https://github.com/tvallas/mtr2mqtt
Author: topo
Author-email: tvallas@iki.fi
Requires-Dist: pyserial
Requires-Dist: paho-mqtt
Requires-Dist: PyYAML
